source_facebook_pages/__init__.py
source_facebook_pages/components.py
source_facebook_pages/manifest.yaml
source_facebook_pages/run.py
source_facebook_pages/schemas/page.json
source_facebook_pages/schemas/page_insights.json
source_facebook_pages/schemas/post.json
source_facebook_pages/schemas/post_insights.json
source_facebook_pages/schemas/shared/adset.json
source_facebook_pages/schemas/shared/advideo.json
source_facebook_pages/schemas/shared/album.json
source_facebook_pages/schemas/shared/application.json
source_facebook_pages/schemas/shared/assigneduser.json
source_facebook_pages/schemas/shared/business.json
source_facebook_pages/schemas/shared/canvas.json
source_facebook_pages/schemas/shared/canvasbodyelement.json
source_facebook_pages/schemas/shared/chatplugin.json
source_facebook_pages/schemas/shared/comment.json
source_facebook_pages/schemas/shared/commercemerchantsettingssetupstatus.json
source_facebook_pages/schemas/shared/commerceorder.json
source_facebook_pages/schemas/shared/coverphoto.json
source_facebook_pages/schemas/shared/customusersettings.json
source_facebook_pages/schemas/shared/engagement.json
source_facebook_pages/schemas/shared/event.json
source_facebook_pages/schemas/shared/group.json
source_facebook_pages/schemas/shared/iguser.json
source_facebook_pages/schemas/shared/imagecopyright.json
source_facebook_pages/schemas/shared/insightsresult.json
source_facebook_pages/schemas/shared/instagramuser.json
source_facebook_pages/schemas/shared/leadgenform.json
source_facebook_pages/schemas/shared/liveencoder.json
source_facebook_pages/schemas/shared/livevideo.json
source_facebook_pages/schemas/shared/location.json
source_facebook_pages/schemas/shared/mailingaddress.json
source_facebook_pages/schemas/shared/mediafingerprint.json
source_facebook_pages/schemas/shared/messagingfeaturereview.json
source_facebook_pages/schemas/shared/messagingfeaturestatus.json
source_facebook_pages/schemas/shared/messengerdestinationpagewelcomemessage.json
airbyte_source_facebook_pages-2.0.4.dist-info/METADATA
airbyte_source_facebook_pages-2.0.4.dist-info/WHEEL
airbyte_source_facebook_pages-2.0.4.dist-info/entry_points.txt
airbyte_source_facebook_pages-2.0.4.dist-info/RECORD
